lion_openai/OpenAIModel.py
lion_openai/OpenAIService.py
lion_openai/__init__.py
lion_openai/api_request.py
lion_openai/data_models.py
lion_openai/match_data_model.py
lion_openai/match_response.py
lion_openai/version.py
lion_openai/audio/__init__.py
lion_openai/audio/base.py
lion_openai/audio/speech_models.py
lion_openai/audio/transcription_models.py
lion_openai/audio/translation_models.py
lion_openai/audio/types.py
lion_openai/batch/__init__.py
lion_openai/batch/base.py
lion_openai/batch/batch_models.py
lion_openai/batch/cancel_batch.py
lion_openai/batch/create_batch.py
lion_openai/batch/list_batch.py
lion_openai/batch/request_object_models.py
lion_openai/batch/retrieve_batch.py
lion_openai/batch/types.py
lion_openai/chat_completions/__init__.py
lion_openai/chat_completions/types.py
lion_openai/chat_completions/util.py
lion_openai/chat_completions/request/__init__.py
lion_openai/chat_completions/request/message_models.py
lion_openai/chat_completions/request/request_body.py
lion_openai/chat_completions/request/response_format.py
lion_openai/chat_completions/request/stream_options.py
lion_openai/chat_completions/request/tool_choice_models.py
lion_openai/chat_completions/request/tool_models.py
lion_openai/chat_completions/request/types.py
lion_openai/chat_completions/response/__init__.py
lion_openai/chat_completions/response/choice_models.py
lion_openai/chat_completions/response/function_models.py
lion_openai/chat_completions/response/log_prob_models.py
lion_openai/chat_completions/response/message_models.py
lion_openai/chat_completions/response/response_body.py
lion_openai/chat_completions/response/types.py
lion_openai/chat_completions/response/usage_models.py
lion_openai/embeddings/__init__.py
lion_openai/embeddings/request_body.py
lion_openai/embeddings/response_body.py
lion_openai/embeddings/types.py
lion_openai/files/__init__.py
lion_openai/files/delete_file.py
lion_openai/files/file_models.py
lion_openai/files/list_files.py
lion_openai/files/retrieve_file.py
lion_openai-1.0.3.dist-info/LICENSE
lion_openai-1.0.3.dist-info/METADATA
lion_openai-1.0.3.dist-info/WHEEL
lion_openai-1.0.3.dist-info/top_level.txt
lion_openai-1.0.3.dist-info/RECORD
