Metadata-Version: 2.1
Name: lion-openai
Version: 1.0.3
Summary: lion openai service integration
Author-email: HaiyangLi <quantocean.li@gmail.com>, Alina Luo <lluo25@fordham.edu>
License: MIT License
Classifier: Programming Language :: Python :: 3
Classifier: Programming Language :: Python :: 3 :: Only
Classifier: Programming Language :: Python :: 3.11
Classifier: Programming Language :: Python :: 3.12
Classifier: Programming Language :: Python :: 3.13
Classifier: Intended Audience :: Developers
Classifier: License :: OSI Approved :: Apache Software License
Classifier: Operating System :: OS Independent
Classifier: Framework :: Pydantic
Classifier: Framework :: Pydantic :: 2
Classifier: Framework :: Pytest
Requires-Python: >=3.11
License-File: LICENSE
Requires-Dist: lion-service>=1.1.1
Requires-Dist: pillow>=11.0.0
Requires-Dist: pyyaml>=6.0.2
